<annotation>
	<folder>dull_green</folder>
	<filename>training_data_2017-11-01T19:03:25.115Z.jpg</filename>
	<path>/data/users/mryan/src/intera/src/tensor/data/dull_green/training_data_2017-11-01T19:03:25.115Z.jpg</path>
	<source>
		<database>Unknown</database>
	</source>
	<size>
		<width>752</width>
		<height>480</height>
		<depth>1</depth>
	</size>
	<segmented>0</segmented>
	<object>
		<name>dull_green_button</name>
		<pose>Unspecified</pose>
		<truncated>0</truncated>
		<difficult>0</difficult>
		<bndbox>
			<xmin>104</xmin>
			<ymin>53</ymin>
			<xmax>185</xmax>
			<ymax>136</ymax>
		</bndbox>
	</object>
</annotation>
